MANIFEST.in
README.md
setup.cfg
setup.py
bin/nirmapper
nirmapper/__init__.py
nirmapper/camera.py
nirmapper/examples.py
nirmapper/exceptions.py
nirmapper/model.py
nirmapper/nirmapper.py
nirmapper/renderer.py
nirmapper/utils.py
nirmapper.egg-info/PKG-INFO
nirmapper.egg-info/SOURCES.txt
nirmapper.egg-info/dependency_links.txt
nirmapper.egg-info/requires.txt
nirmapper.egg-info/top_level.txt
nirmapper/resources/__init__.py
nirmapper/resources/images/__init__.py
nirmapper/resources/images/cube_1.png
nirmapper/resources/images/cube_2.png
nirmapper/resources/images/cube_3.png
nirmapper/resources/images/cube_4.png
nirmapper/resources/images/cube_5.png
nirmapper/resources/images/cube_6.png
nirmapper/resources/images/elefant_0.png
nirmapper/resources/images/elefant_1.png
nirmapper/resources/images/elefant_2.png
nirmapper/resources/images/elefant_3.png
nirmapper/resources/images/elefant_4.png
nirmapper/resources/images/overlap.png
nirmapper/resources/images/result.png
nirmapper/resources/images/sample1.jpg
nirmapper/resources/images/sample2.jpg
nirmapper/resources/images/texture_11_adjusted.bmp
nirmapper/resources/images/texture_14_adjusted.bmp
nirmapper/resources/images/texture_19_adjusted.bmp
nirmapper/resources/images/texture_1_adjusted.bmp
nirmapper/resources/images/texture_4_adjusted.bmp
nirmapper/resources/images/texture_8_adjusted.bmp
nirmapper/resources/models/4_downsized_adjusted.mtl
nirmapper/resources/models/4_downsized_adjusted.obj
nirmapper/resources/models/4_downsized_adjusted.obj.bin
nirmapper/resources/models/4_downsized_adjusted.obj.json
nirmapper/resources/models/4_downsized_adjusted_retriangulated.obj
nirmapper/resources/models/4_downsized_adjusted_retriangulated.obj.bin
nirmapper/resources/models/4_downsized_adjusted_retriangulated.obj.json
nirmapper/resources/models/elefante.mtl
nirmapper/resources/models/elefante.obj
nirmapper/resources/models/elefante.obj.bin
nirmapper/resources/models/elefante.obj.json
nirmapper/resources/xmlExample/1.bmp
nirmapper/resources/xmlExample/1.xml
nirmapper/resources/xmlExample/tooth.obj
tests/__init__.py
tests/test_camera.py
tests/test_indicesFormats.py
tests/test_indicesFormatter.py
