Metadata-Version: 2.1
Name: nirmapper
Version: 1.1.10
Summary: Python library to map textures on a Wavefront .obj files.
Home-page: https://github.com/fechbmaster/3DNIRmapper
Author: fechbmaster
Author-email: bernd.fecht1@hs-augsburg.de
License: Apache-2.0
Platform: UNKNOWN
Requires-Python: >2.7
